<?xml version="1.0" encoding="UTF-8"?>
<PathOfBuilding>
	<Build level="99" targetVersion="3_0" pantheonMajorGod="Solaris" bandit="None" className="Ranger" ascendClassName="Pathfinder" characterLevelAutoMode="true" mainSocketGroup="2" viewMode="TREE" pantheonMinorGod="Ralakesh">
		<PlayerStat stat="AverageHit" value="0"/>
		<PlayerStat stat="AverageBurstDamage" value="0"/>
		<PlayerStat stat="Speed" value="4.3333333333333"/>
		<PlayerStat stat="TrapThrowingTime" value="0.23076923076923"/>
		<PlayerStat stat="TotemPlacementTime" value="0.67873303167421"/>
		<PlayerStat stat="PreEffectiveCritChance" value="0"/>
		<PlayerStat stat="CritChance" value="0"/>
		<PlayerStat stat="CritMultiplier" value="1.5"/>
		<PlayerStat stat="HitChance" value="100"/>
		<PlayerStat stat="TotalDPS" value="0"/>
		<PlayerStat stat="TotalDot" value="0"/>
		<PlayerStat stat="WithBleedDPS" value="0"/>
		<PlayerStat stat="WithIgniteDPS" value="0"/>
		<PlayerStat stat="WithPoisonDPS" value="0"/>
		<PlayerStat stat="TotalDotDPS" value="0"/>
		<PlayerStat stat="CullingDPS" value="0"/>
		<PlayerStat stat="ReservationDPS" value="0"/>
		<PlayerStat stat="CombinedDPS" value="0"/>
		<PlayerStat stat="AreaOfEffectRadius" value="52"/>
		<PlayerStat stat="ManaCost" value="139"/>
		<PlayerStat stat="ManaPercentCost" value="0"/>
		<PlayerStat stat="ManaPerSecondCost" value="602.33333333333"/>
		<PlayerStat stat="ManaPercentPerSecondCost" value="0"/>
		<PlayerStat stat="LifeCost" value="0"/>
		<PlayerStat stat="LifePercentCost" value="0"/>
		<PlayerStat stat="LifePerSecondCost" value="0"/>
		<PlayerStat stat="LifePercentPerSecondCost" value="0"/>
		<PlayerStat stat="ESCost" value="0"/>
		<PlayerStat stat="ESPerSecondCost" value="0"/>
		<PlayerStat stat="ESPercentPerSecondCost" value="0"/>
		<PlayerStat stat="RageCost" value="0"/>
		<PlayerStat stat="SoulCost" value="0"/>
		<PlayerStat stat="Str" value="179"/>
		<PlayerStat stat="ReqStr" value="159"/>
		<PlayerStat stat="Dex" value="389"/>
		<PlayerStat stat="ReqDex" value="222"/>
		<PlayerStat stat="Int" value="104"/>
		<PlayerStat stat="ReqInt" value="155"/>
		<PlayerStat stat="Devotion" value="0"/>
		<PlayerStat stat="TotalEHP" value="56021.63727326"/>
		<PlayerStat stat="PhysicalMaximumHitTaken" value="32771"/>
		<PlayerStat stat="LightningMaximumHitTaken" value="44687"/>
		<PlayerStat stat="FireMaximumHitTaken" value="44687"/>
		<PlayerStat stat="ColdMaximumHitTaken" value="61215"/>
		<PlayerStat stat="ChaosMaximumHitTaken" value="12753"/>
		<PlayerStat stat="Life" value="5999"/>
		<PlayerStat stat="Spec:LifeInc" value="180"/>
		<PlayerStat stat="LifeUnreserved" value="5999"/>
		<PlayerStat stat="LifeRecoverable" value="5999"/>
		<PlayerStat stat="LifeUnreservedPercent" value="100"/>
		<PlayerStat stat="LifeRegenRecovery" value="2011.3"/>
		<PlayerStat stat="LifeLeechGainRate" value="0"/>
		<PlayerStat stat="Mana" value="680"/>
		<PlayerStat stat="Spec:ManaInc" value="0"/>
		<PlayerStat stat="ManaUnreserved" value="36"/>
		<PlayerStat stat="ManaUnreservedPercent" value="5.2941176470588"/>
		<PlayerStat stat="ManaRegenRecovery" value="11.9"/>
		<PlayerStat stat="ManaLeechGainRate" value="0"/>
		<PlayerStat stat="EnergyShield" value="262"/>
		<PlayerStat stat="EnergyShieldRecoveryCap" value="262"/>
		<PlayerStat stat="Spec:EnergyShieldInc" value="25"/>
		<PlayerStat stat="EnergyShieldRegenRecovery" value="0"/>
		<PlayerStat stat="EnergyShieldLeechGainRate" value="0"/>
		<PlayerStat stat="Ward" value="0"/>
		<PlayerStat stat="RageRegenRecovery" value="0"/>
		<PlayerStat stat="Evasion" value="17050"/>
		<PlayerStat stat="Spec:EvasionInc" value="58"/>
		<PlayerStat stat="MeleeEvadeChance" value="67"/>
		<PlayerStat stat="ProjectileEvadeChance" value="67"/>
		<PlayerStat stat="Armour" value="1075"/>
		<PlayerStat stat="Spec:ArmourInc" value="0"/>
		<PlayerStat stat="PhysicalDamageReduction" value="37"/>
		<PlayerStat stat="BlockChance" value="0"/>
		<PlayerStat stat="SpellBlockChance" value="0"/>
		<PlayerStat stat="AttackDodgeChance" value="0"/>
		<PlayerStat stat="SpellDodgeChance" value="0"/>
		<PlayerStat stat="SpellSuppressionChance" value="100"/>
		<PlayerStat stat="FireResist" value="75"/>
		<PlayerStat stat="FireResistOverCap" value="44"/>
		<PlayerStat stat="ColdResist" value="75"/>
		<PlayerStat stat="ColdResistOverCap" value="97"/>
		<PlayerStat stat="LightningResist" value="75"/>
		<PlayerStat stat="LightningResistOverCap" value="26"/>
		<PlayerStat stat="ChaosResist" value="36"/>
		<PlayerStat stat="ChaosResistOverCap" value="0"/>
		<PlayerStat stat="EffectiveMovementSpeedMod" value="2.5064"/>
		<PlayerStat stat="FullDPS" value="0"/>
		<PlayerStat stat="FullDotDPS" value="0"/>
		<PlayerStat stat="PowerCharges" value="3"/>
		<PlayerStat stat="PowerChargesMax" value="3"/>
		<PlayerStat stat="FrenzyCharges" value="4"/>
		<PlayerStat stat="FrenzyChargesMax" value="4"/>
		<PlayerStat stat="EnduranceCharges" value="0"/>
		<PlayerStat stat="EnduranceChargesMax" value="3"/>
		<PlayerStat stat="ActiveTotemLimit" value="1"/>
		<TimelessData devotionVariant2="1" searchListFallback="" searchList="" socketFilterDistance="0" devotionVariant1="1"/>
	</Build>
	<Import exportParty="false"/>
	<Party destination="All" ShowAdvanceTools="false" append="false"/>
	<Tree activeSpec="2">
		<Spec title="Bare Minimum" ascendClassId="3" masteryEffects="{6570,13382},{37616,20694},{65528,57074},{57949,34420},{20736,10815},{292,47642}" nodes="22266,32117,1648,5237,63150,59766,36221,57949,50338,58271,4011,63251,40813,6250,64265,61653,25260,27788,20736,11431,20480,9877,44988,14400,65528,49900,12143,24083,20546,6363,41420,65210,6538,36287,6570,45035,18769,16882,1697,19858,3676,28859,3656,46277,20807,58968,35894,31359,3359,9206,59866,21835,50459,51101,49978,32662,18770,60440,4656,31585,33783,36858,53114,6799,1822,14156,40362,17790,34678,11811,26528,22217,63194,8938,62744,27962,292,63293,22535,30825,59370,29454,64111,25058,32555,9355,16544,55571,63795,12801,59556,12412,43684,4502,6383,11364,48099,37663,37616,29937,30679,1461,38190,38662,30767,36242,59606,1325,31501,8544,45593,5823,19069,31471" treeVersion="3_21" classId="2">
			<URL>
				https://www.pathofexile.com/passive-skill-tree/AAAABgIDcFb6fXUGcBR19q7pdo194l3EouOfD6v3E59tGGr7CfDVYqxsjFEALKdQACaVr7w4QP_4wuwvb14TUEIY26HM_roZio2_Gaqv60lRQfIGoU2SDlxwuw5ItMVRR-ZYjDZ6fw0fI_bp2lVLx53DOn-WSVLsGBIwe2GD94_6z3oajwceN0ydqkV-h3YuI2egVsn22iLq9RhtOgEk9z1YB3hp5-pzDmHifyski0Cg2RP5MzIB6KQwfKqkEZYY7yxku-OTH5LwdPF31wW1lS6XBngvjZLo1gUtew0hYLIZFr9KfXrvAAaGdOJdKj9RAN7y__g0RhmquhoBJFDWkvA=
			</URL>
			<Sockets>
				<Socket nodeId="54127" itemId="5"/>
				<Socket nodeId="33989" itemId="5"/>
				<Socket nodeId="60735" itemId="5"/>
			</Sockets>
		</Spec>
		<Spec title="Endgame" ascendClassId="3" masteryEffects="{6570,13382},{57949,34420},{37616,20694},{65528,57074},{20736,10815},{53615,28638},{28903,62897},{292,47642}" nodes="1648,5237,63150,25067,46289,44988,64265,1325,30338,27788,9877,14400,39861,65528,41420,65210,23066,16882,1697,28903,3656,20807,22217,29933,9206,18769,51101,60440,38190,59606,29937,14156,40362,17790,37616,26528,4656,22535,63194,59370,29454,64111,32555,25058,63293,59556,37663,30767,8544,31471,22266,32117,24083,28859,59766,36221,53615,50338,58271,4011,63251,14292,6250,61653,25260,20736,45593,49900,20546,6363,6538,6570,19858,3676,58968,31359,3359,50459,49978,18770,48099,36858,6799,1822,54127,19140,34678,11811,5823,33783,57949,8938,31501,27962,21835,38662,45035,53114,292,62744,20480,12143,12801,9355,30825,55571,63795,36287,16544,35894,43684,18103,6383,11364,31585,60735,59866,12412,30679,1461,46408,46277,62791,36242,4502,40813,51212,31315,32662,33989,19069,11431" treeVersion="3_21" classId="2">
			<URL>
				https://www.pathofexile.com/passive-skill-tree/AAAABgIDggZwFHX2rmHrtNGvvPsJBS12gmyMJpU4QJu1__ihzP66WhpB8gahcOcOSFFHVsl07SP2SVHHnewYlS7o1nTxN0ydqkV-kvBnoBIwWAf22ufqcw5_K2Hi9z3opJMfeC8hYHrvVvp9dV4TcLvpdo190W_EouOfD6v3EzfUGGrw1WKsUQCyGcLsUEIY2xmKGapNkg5c5lh6fw0fwzpJUrvjj_oajwce029KxId2LiMWv4P34l0i6nsNbTpVS5cGr-vPegEk9RhQAC9vMgEki3hp2RP5M42_QKCMNqqkRrcY7yxke2HtP-naMHx31wW1tUi0xfVHjZIRlp9tyAx6U3-WhMVKfSynAAje8v_49bFw51DWkvBv3tFvKj9RADRGGaqGdOJduhoBJA==
			</URL>
			<Sockets>
				<Socket nodeId="54127" itemId="5"/>
				<Socket nodeId="33989" itemId="5"/>
				<Socket nodeId="60735" itemId="5"/>
			</Sockets>
		</Spec>
	</Tree>
	<Notes>
		Before Slavedriver&apos;s Hand you can go EB with some ES on gear and  use The Sorrow of the Divine flask to sustain your energy shield. You can also run Malevolence on Divine Blessing at this point.

If you have the &quot;X% chance to summon two totems&quot; node on your bow tree, you can drop multiple totems support and use empower instead. Make sure to pick up the totem mastery for 30% chance for two totems as well if you do.

Before you have an elder quiver or Divergent HoAg you can annoint Toxic Strikes and/or use Icefang Orbit

Cluster setup would be a large 8 passive phys cluster into a totem medium with the node that gives you onslaught, and the flask duration medium that gives you alchemist genius. The other nodes are free to fill in how you want.


^xFFFF77Endgame bow(+1, +2 support gems, chaos damage over time, faster poison, chaos dot mult)^7
^xC8C8C81. Alteration roll a Hunter Maraketh Bow for T1 faster poison or T1 generic dot mult or use an essence of Misery(skip step 2 if essence spam)
2. Regal
3. Annul until you have only the desired mod left ON A RARE BOW, if you miss start over
4. Craft &quot;Can have up to 3 Crafted Modifiers&quot;(^xD020902 divines^7^xC8C8C8) and &quot;Cannot roll Attack Modifiers&quot;(^xD020901 divine^xC8C8C8^7)^xC8C8C8
5. Slam ^xD020902 exalts^7^xC8C8C8(closing eyes is optional), this will guarantee +1 socketed gems and chaos damage over time
6. Remove crafted mods
7. Craft &quot;Can have up to 3 Crafted Modifiers&quot;(^xD020902 divines^7^xC8C8C8)^xC8C8C8, &quot;Chaos Damage Over Time Multiplier&quot; and &quot;+2 to Level of Socketed Support Gems&quot;(^xD020902 exalts^7^xC8C8C8)
8. Done!^7
	</Notes>
	<Skills sortGemsByDPSField="CombinedDPS" activeSkillSet="1" sortGemsByDPS="true" defaultGemQuality="20" defaultGemLevel="normalMaximum" showSupportGemTypes="ALL" showAltQualityGems="false">
		<SkillSet id="1">
			<Skill mainActiveSkillCalcs="1" includeInFullDPS="false" label="" enabled="true" mainActiveSkill="1">
				<Gem enableGlobal2="true" level="20" enableGlobal1="true" skillId="Grace" qualityId="Default" gemId="Metadata/Items/Gems/SkillGemGrace" quality="0" enabled="true" count="1" nameSpec="Grace"/>
				<Gem enableGlobal2="true" level="20" enableGlobal1="true" skillId="Purity" qualityId="Default" gemId="Metadata/Items/Gems/SkillGemPurity" quality="0" enabled="true" count="1" nameSpec="Purity of Elements"/>
			</Skill>
			<Skill mainActiveSkillCalcs="1" includeInFullDPS="false" label="Damage Setup if Empower AND multitotem on bow" enabled="true" slot="Weapon 1" mainActiveSkill="1">
				<Gem enableGlobal2="true" level="21" enableGlobal1="true" skillId="RejuvenationTotem" qualityId="Default" gemId="Metadata/Items/Gems/SkillGemRejuvenationTotem" quality="20" enabled="true" count="1" nameSpec="Rejuvenation Totem"/>
				<Gem enableGlobal2="true" level="4" enableGlobal1="true" skillId="SupportAdditionalLevel" qualityId="Default" gemId="Metadata/Items/Gems/SupportGemAdditionalLevel" quality="20" enabled="true" count="1" nameSpec="Empower"/>
				<Gem enableGlobal2="true" level="20" enableGlobal1="true" skillId="SupportTrap" qualityId="Default" gemId="Metadata/Items/Gems/SupportGemTrap" quality="20" enabled="true" count="1" nameSpec="Trap"/>
				<Gem enableGlobal2="true" level="20" enableGlobal1="true" skillId="SupportMultiTrap" qualityId="Default" gemId="Metadata/Items/Gems/SupportGemMultiTrap" quality="20" enabled="true" count="1" nameSpec="Multiple Traps"/>
				<Gem enableGlobal2="true" level="20" enableGlobal1="true" skillId="SupportClusterTrap" qualityId="Default" gemId="Metadata/Items/Gems/SupportGemClusterTrap" quality="20" enabled="true" count="1" nameSpec="Cluster Traps"/>
				<Gem enableGlobal2="true" level="20" enableGlobal1="true" skillId="SupportGemFrenzyPowerOnTrapTrigger" qualityId="Default" gemId="Metadata/Items/Gems/SupportGemFrenzyPowerOnTrapTrigger" quality="20" enabled="true" count="1" nameSpec="Charged Traps"/>
			</Skill>
			<Skill mainActiveSkillCalcs="1" includeInFullDPS="false" label="Damage Setup if no Empower" enabled="true" slot="Weapon 1" mainActiveSkill="1">
				<Gem enableGlobal2="true" level="21" enableGlobal1="true" skillId="RejuvenationTotem" qualityId="Default" gemId="Metadata/Items/Gems/SkillGemRejuvenationTotem" quality="20" enabled="true" count="1" nameSpec="Rejuvenation Totem"/>
				<Gem enableGlobal2="true" level="20" enableGlobal1="true" skillId="SupportMultiTotem" qualityId="Default" gemId="Metadata/Items/Gems/SupportGemMultiTotem" quality="20" enabled="true" count="1" nameSpec="Multiple Totems"/>
				<Gem enableGlobal2="true" level="20" enableGlobal1="true" skillId="SupportTrap" qualityId="Default" gemId="Metadata/Items/Gems/SupportGemTrap" quality="20" enabled="true" count="1" nameSpec="Trap"/>
				<Gem enableGlobal2="true" level="20" enableGlobal1="true" skillId="SupportMultiTrap" qualityId="Default" gemId="Metadata/Items/Gems/SupportGemMultiTrap" quality="20" enabled="true" count="1" nameSpec="Multiple Traps"/>
				<Gem enableGlobal2="true" level="20" enableGlobal1="true" skillId="SupportClusterTrap" qualityId="Default" gemId="Metadata/Items/Gems/SupportGemClusterTrap" quality="20" enabled="true" count="1" nameSpec="Cluster Traps"/>
				<Gem enableGlobal2="true" level="20" enableGlobal1="true" skillId="SupportGemFrenzyPowerOnTrapTrigger" qualityId="Default" gemId="Metadata/Items/Gems/SupportGemFrenzyPowerOnTrapTrigger" quality="20" enabled="true" count="1" nameSpec="Charged Traps"/>
			</Skill>
			<Skill mainActiveSkillCalcs="1" includeInFullDPS="false" label="" enabled="true" mainActiveSkill="1">
				<Gem enableGlobal2="true" level="21" enableGlobal1="true" skillId="Slither" qualityId="Default" gemId="Metadata/Items/Gems/SkillGemWitheringStep" quality="20" enabled="true" count="1" nameSpec="Withering Step"/>
				<Gem enableGlobal2="true" level="20" enableGlobal1="true" skillId="Despair" qualityId="Default" gemId="Metadata/Items/Gems/SkillGemVulnerability" quality="20" enabled="true" count="1" nameSpec="Despair"/>
				<Gem enableGlobal2="true" level="20" enableGlobal1="true" skillId="TemporalChains" qualityId="Default" gemId="Metadata/Items/Gems/SkillGemTemporalChains" quality="20" enabled="true" count="1" nameSpec="Temporal Chains"/>
			</Skill>
			<Skill mainActiveSkillCalcs="1" includeInFullDPS="false" label="" enabled="true" mainActiveSkill="1">
				<Gem enableGlobal2="true" skillMinionSkillCalcs="1" level="20" enableGlobal1="true" skillId="HeraldOfAgony" skillMinionSkill="1" qualityId="Alternate2" gemId="Metadata/Items/Gems/HeraldOfAgony" quality="20" enabled="true" count="1" nameSpec="Herald of Agony" skillMinion="HeraldOfAgonySpiderPlated"/>
			</Skill>
			<Skill mainActiveSkillCalcs="1" includeInFullDPS="false" label="" enabled="true" mainActiveSkill="1">
				<Gem enableGlobal2="true" level="20" enableGlobal1="true" skillId="FlameDash" qualityId="Default" gemId="Metadata/Items/Gems/SkillGemFlameDash" quality="20" enabled="true" count="1" nameSpec="Flame Dash"/>
				<Gem enableGlobal2="true" skillMinionSkillCalcs="1" level="20" enableGlobal1="true" skillId="BlinkArrow" skillMinionSkill="1" qualityId="Default" gemId="Metadata/Items/Gems/SkillGemBlinkArrow" quality="20" enabled="true" count="1" nameSpec="Blink Arrow" skillMinion="Clone"/>
				<Gem enableGlobal2="true" level="20" enableGlobal1="true" skillId="SupportAdditionalCooldown" qualityId="Default" gemId="Metadata/Items/Gems/SupportGemSecondWind" quality="20" enabled="true" count="1" nameSpec="Second Wind"/>
			</Skill>
			<Skill mainActiveSkillCalcs="1" includeInFullDPS="false" label="" enabled="true" mainActiveSkill="1">
				<Gem enableGlobal2="true" level="1" enableGlobal1="true" skillId="SupportCastOnDamageTaken" qualityId="Default" gemId="Metadata/Items/Gems/SupportGemCastOnDamageTaken" quality="20" enabled="true" count="1" nameSpec="Cast when Damage Taken"/>
				<Gem enableGlobal2="true" level="3" enableGlobal1="true" skillId="ImmortalCall" qualityId="Default" gemId="Metadata/Items/Gems/SkillGemImmortalCall" quality="20" enabled="true" count="1" nameSpec="Immortal Call"/>
			</Skill>
		</SkillSet>
	</Skills>
	<Calcs>
		<Input name="misc_buffMode" string="EFFECTIVE"/>
		<Input name="skill_number" number="2"/>
		<Section subsection="ViewSkillDetails" collapsed="false" id="SkillSelect"/>
		<Section subsection="SkillHitDamage" collapsed="false" id="HitDamage"/>
		<Section subsection="ExertingWarcries" collapsed="false" id="Warcries"/>
		<Section subsection="SkillDamageoverTime" collapsed="false" id="Dot"/>
		<Section subsection="AttackCastRate" collapsed="false" id="Speed"/>
		<Section subsection="Crits" collapsed="false" id="Crit"/>
		<Section subsection="Impale" collapsed="false" id="Impale"/>
		<Section subsection="SkilltypespecificStats" collapsed="false" id="SkillTypeStats"/>
		<Section subsection="Accuracy" collapsed="false" id="HitChance"/>
		<Section subsection="Bleed" collapsed="false" id="Bleed"/>
		<Section subsection="Poison" collapsed="false" id="Poison"/>
		<Section subsection="Ignite" collapsed="false" id="Ignite"/>
		<Section subsection="Decay" collapsed="false" id="Decay"/>
		<Section subsection="LeechGainonHit" collapsed="false" id="LeechGain"/>
		<Section subsection="NonDamagingAilments" collapsed="false" id="EleAilments"/>
		<Section subsection="OtherEffects" collapsed="false" id="MiscEffects"/>
		<Section subsection="Attributes" collapsed="false" id="Attributes"/>
		<Section subsection="Life" collapsed="false" id="Life"/>
		<Section subsection="Mana" collapsed="false" id="Mana"/>
		<Section subsection="EnergyShield" collapsed="false" id="EnergyShield"/>
		<Section subsection="Ward" collapsed="false" id="Ward"/>
		<Section subsection="Resists" collapsed="false" id="Resist"/>
		<Section subsection="Armour" collapsed="false" id="Armour"/>
		<Section subsection="Evasion" collapsed="false" id="Evasion"/>
		<Section subsection="DamageAvoidance" collapsed="false" id="DamageAvoidance"/>
		<Section subsection="Block" collapsed="false" id="DamageAvoidance"/>
		<Section subsection="Dodge" collapsed="false" id="DamageAvoidance"/>
		<Section subsection="SpellSuppression" collapsed="false" id="DamageAvoidance"/>
		<Section subsection="Flasks" collapsed="false" id="Flasks"/>
		<Section subsection="UtilityFlasks" collapsed="true" id="Flasks"/>
		<Section subsection="LifeFlasks" collapsed="true" id="Flasks"/>
		<Section subsection="ManaFlasks" collapsed="true" id="Flasks"/>
		<Section subsection="Rage" collapsed="true" id="Rage"/>
		<Section subsection="OtherDefences" collapsed="false" id="MiscDefences"/>
		<Section subsection="StunDuration" collapsed="false" id="MiscDefences"/>
		<Section subsection="OtherAvoidance" collapsed="false" id="MiscDefences"/>
		<Section subsection="OtherAilmentDefences" collapsed="true" id="MiscDefences"/>
		<Section subsection="DamageTaken" collapsed="false" id="DamageTaken"/>
		<Section subsection="DamagingHits" collapsed="false" id="DamageTaken"/>
		<Section subsection="EffectiveHealthPool" collapsed="false" id="DamageTaken"/>
		<Section subsection="MaximumHitTaken" collapsed="false" id="DamageTaken"/>
		<Section subsection="DotsandDegens" collapsed="false" id="DamageTaken"/>
		<Section subsection="RecoupandHitTakenOverTime" collapsed="true" id="DamageTaken"/>
	</Calcs>
	<TreeView searchStr="" zoomY="-142.9479627817" zoomLevel="2" showStatDifferences="true" zoomX="-515.80792611724"/>
	<Items activeItemSet="1" useSecondWeaponSet="false">
		<Item id="1">
			Rarity: UNIQUE
Slavedriver&apos;s Hand
Ambush Mitts
Evasion: 296
EvasionBasePercentile: 0.4797
Energy Shield: 62
EnergyShieldBasePercentile: 0.4855
League: Incursion
Quality: 20
Sockets: G-G-G-G
LevelReq: 45
Implicits: 0
{range:0.5}+(30-40) to Dexterity
{range:0.5}(200-250)% increased Evasion and Energy Shield
{range:0.5}(20-30)% reduced Trap Throwing Speed
Skills which throw Traps Cost Life instead of Mana
{range:0.5}Skills used by Traps have (10-20)% increased Area of Effect
Increases and Reductions to Cast Speed also Apply to Trap Throwing Speed
10% chance to gain an Endurance, Frenzy or Power Charge when any of your Traps is Triggered by an Enemy
			<ModRange range="0.5" id="1"/>
			<ModRange range="0.5" id="2"/>
			<ModRange range="0.5" id="3"/>
			<ModRange range="0.5" id="4"/>
			<ModRange range="0.5" id="5"/>
			<ModRange range="0.5" id="6"/>
		</Item>
		<Item variant="3" id="2">
			Rarity: UNIQUE
Lightning Coil
Desert Brigandine
Armour: 925
ArmourBasePercentile: 0.4681
Evasion: 925
EvasionBasePercentile: 0.4681
Variant: Pre 1.3.0
Variant: Pre 3.19.0
Variant: Current
Selected Variant: 3
Desert Brigandine
Quality: 20
Sockets: G-G-G-G-G-G
LevelReq: 60
Implicits: 0
{range:0.5}Adds 1 to (20-30) Lightning Damage to Attacks
{range:0.5}(90-120)% increased Armour and Evasion
{range:0.5}+(60-80) to maximum Life
-60% to Lightning Resistance
{variant:1}40% of Physical Damage from Hits taken as Lightning Damage
{variant:2}30% of Physical Damage from Hits taken as Lightning Damage
{variant:3}50% of Physical Damage from Hits taken as Lightning Damage
			<ModRange range="0.5" id="1"/>
			<ModRange range="0.5" id="2"/>
			<ModRange range="0.5" id="3"/>
			<ModRange range="0.5" id="4"/>
			<ModRange range="0.5" id="5"/>
			<ModRange range="0.5" id="6"/>
			<ModRange range="0.5" id="7"/>
		</Item>
		<Item id="3">
			Rarity: RARE
Bow if Empower
Maraketh Bow
Hunter Item
Item Level: 83
Quality: 20
Sockets: R-R-G-G-G G
LevelReq: 71
Implicits: 1
10% increased Movement Speed
+1 to Level of Socketed Gems
66% increased Chaos Damage over Time
Poisons you inflict deal Damage 24% faster
{crafted}Can have up to 3 Crafted Modifiers
{crafted}+18% to Chaos Damage over Time Multiplier
{tags:unveiled_mod,gem}{crafted}+2 to Level of Socketed Support Gems
{crucible}Adds 48 to 71 Fire Damage
{crucible}+1.2% to Critical Strike Chance
{crucible}25% reduced Totem Life
{crucible}-500 to Accuracy Rating
{crucible}20% chance to Ignite
{crucible}25% reduced Totem Placement speed
			<ModRange range="0.5" id="1"/>
			<ModRange range="0.5" id="2"/>
			<ModRange range="0.5" id="3"/>
			<ModRange range="0.5" id="4"/>
			<ModRange range="0.5" id="6"/>
			<ModRange range="0.5" id="7"/>
			<ModRange range="0.5" id="8"/>
			<ModRange range="0.5" id="9"/>
			<ModRange range="0.5" id="10"/>
			<ModRange range="0.5" id="11"/>
			<ModRange range="0.5" id="12"/>
			<ModRange range="0.5" id="13"/>
		</Item>
		<Item id="4">
			Rarity: RARE
Pandemonium Quill
Vile Arrow Quiver
Elder Item
Item Level: 85
LevelReq: 64
Implicits: 1
Gain 14% of Physical Damage as Extra Chaos Damage
+89 to maximum Life
+20% to Fire Resistance
+36% to Cold Resistance
20% chance to Poison on Hit
26% increased Damage with Poison
{crafted}+270 to Evasion Rating
{crafted}+23 to maximum Energy Shield
			<ModRange range="0.5" id="1"/>
			<ModRange range="0.5" id="2"/>
			<ModRange range="0.5" id="3"/>
			<ModRange range="0.5" id="4"/>
			<ModRange range="0.5" id="5"/>
			<ModRange range="0.5" id="6"/>
			<ModRange range="0.5" id="7"/>
			<ModRange range="0.5" id="8"/>
		</Item>
		<Item id="5">
			Rarity: RARE
Jewel
Crimson Jewel
Crafted: true
Prefix: {range:0.5}PercentIncreasedLifeJewel
Prefix: {range:1}TotemLifeJewel
Suffix: None
Suffix: None
LevelReq: 0
Implicits: 0
6% increased maximum Life
12% increased Totem Life
			<ModRange range="0.5" id="1"/>
			<ModRange range="0.5" id="2"/>
		</Item>
		<Item id="6">
			Rarity: RARE
Pandemonium Crown
Deicide Mask
Evasion: 254
EvasionBasePercentile: 0.1954
Energy Shield: 58
EnergyShieldBasePercentile: 0.1905
Searing Exarch Item
Eater of Worlds Item
Item Level: 84
Quality: 20
Sockets: B-G B-G
LevelReq: 67
Implicits: 2
7% of Physical Damage from Hits taken as Cold Damage
10% increased Temporal Chains Curse Effect
+5% chance to Suppress Spell Damage
+22 to Dexterity
+16 to Evasion Rating
+109 to maximum Life
+45% to Lightning Resistance
{crafted}7% of Physical Damage from Hits taken as Fire Damage
			<ModRange range="0.5" id="1"/>
			<ModRange range="0.5" id="2"/>
			<ModRange range="0.5" id="3"/>
			<ModRange range="0.5" id="4"/>
			<ModRange range="0.5" id="5"/>
			<ModRange range="0.5" id="6"/>
			<ModRange range="0.5" id="7"/>
			<ModRange range="0.5" id="8"/>
		</Item>
		<Item id="7">
			Rarity: RARE
Evasion/Energy Shield Boots
Fugitive Boots
Evasion: 134
EvasionBasePercentile: 0
Energy Shield: 38
EnergyShieldBasePercentile: 0
Searing Exarch Item
Eater of Worlds Item
Crafted: true
Prefix: None
Prefix: {range:0.461}IncreasedLife8
Prefix: {range:0.5}MovementVelocity5
Suffix: {range:0.5}ChaosResist4
Suffix: {range:0.972}ColdResist6
Suffix: {range:0.736}ChanceToSuppressSpells5__
Quality: 20
Sockets: B-B-B-B
LevelReq: 70
Implicits: 2
{exarch}4% increased Action Speed
{tags:physical,chaos}{eater}While a Unique Enemy is in your Presence, Gain 6% of Physical Damage as Extra Chaos Damage
+14% chance to Suppress Spell Damage
+84 to maximum Life
+41% to Cold Resistance
+23% to Chaos Resistance
30% increased Movement Speed
			<ModRange range="0.5" id="1"/>
			<ModRange range="0.5" id="2"/>
			<ModRange range="0.5" id="3"/>
			<ModRange range="0.5" id="4"/>
			<ModRange range="0.5" id="5"/>
			<ModRange range="0.5" id="6"/>
			<ModRange range="0.5" id="7"/>
		</Item>
		<Item id="8">
			Rarity: RARE
Amulet
Amber Amulet
Hunter Item
Crafted: true
Prefix: {range:0.5}PhysicalDamageLifeLeechInfluence1
Prefix: {range:0.845}IncreasedLife6
Prefix: {range:0.5}GlobalSkillGemLevel1
Suffix: {range:0.592}LightningResist7
Suffix: {range:1}FireResist4
Suffix: None
LevelReq: 60
Implicits: 2
{crafted}Allocates Primal Manifestation
{tags:attribute}{range:1}+(20-30) to Strength
+68 to maximum Life
+29% to Fire Resistance
+44% to Lightning Resistance
0.4% of Physical Damage Leeched as Life
+1 to Level of all Skill Gems
			<ModRange range="0.5" id="1"/>
			<ModRange range="1" id="2"/>
			<ModRange range="0.5" id="3"/>
			<ModRange range="0.5" id="4"/>
			<ModRange range="0.5" id="5"/>
			<ModRange range="0.5" id="6"/>
			<ModRange range="0.5" id="7"/>
		</Item>
		<Item id="9">
			Rarity: RARE
Chaos Resistance Ring
Amethyst Ring
Crafted: true
Prefix: {range:0.845}IncreasedLife6
Prefix: None
Prefix: None
Suffix: {range:0.394}FireResist7
Suffix: {range:1}IncreasedCastSpeed3
Suffix: {range:0.732}LightningResist7
LevelReq: 57
Implicits: 1
{tags:chaos,resistance}{range:1}+(17-23)% to Chaos Resistance
16% increased Cast Speed
+68 to maximum Life
+43% to Fire Resistance
+44% to Lightning Resistance
			<ModRange range="1" id="1"/>
			<ModRange range="0.5" id="2"/>
			<ModRange range="0.5" id="3"/>
			<ModRange range="0.5" id="4"/>
			<ModRange range="0.5" id="5"/>
		</Item>
		<Item id="10">
			Rarity: RARE
Belt
Heavy Belt
Crafted: true
Prefix: {range:0.225}IncreasedLife9
Prefix: None
Prefix: None
Suffix: {range:0.958}Strength8
Suffix: {range:0.563}ColdResist7
Suffix: {range:0.599}BeltIncreasedFlaskChargesGained6
LevelReq: 67
Implicits: 1
{tags:attribute}{range:1}+(25-35) to Strength
+50 to Strength
+92 to maximum Life
+44% to Cold Resistance
38% increased Flask Charges gained
			<ModRange range="1" id="1"/>
			<ModRange range="0.5" id="2"/>
			<ModRange range="0.5" id="3"/>
			<ModRange range="0.5" id="4"/>
			<ModRange range="0.5" id="5"/>
		</Item>
		<Item id="11">
			Rarity: MAGIC
Saturated Divine Life Flask of Assuaging
Crafted: true
Prefix: {range:1}FlaskIncreasedRecoveryAmount5
Suffix: {range:1}FlaskBleedCorruptingBloodImmunity4_
Quality: 20
LevelReq: 64
Implicits: 0
70% increased Amount Recovered
33% reduced Recovery rate
Grants Immunity to Bleeding for 17 seconds if used while Bleeding
Grants Immunity to Corrupted Blood for 17 seconds if used while affected by Corrupted Blood
			<ModRange range="0.5" id="1"/>
			<ModRange range="0.5" id="2"/>
			<ModRange range="0.5" id="3"/>
		</Item>
		<Item id="12">
			Rarity: MAGIC
Flagellant&apos;s Quicksilver Flask of the Cheetah
Crafted: true
Prefix: {range:1}FlaskFullRechargeOnHit5___
Suffix: {range:1}FlaskBuffMovementSpeedWhileHealing3
Quality: 20
LevelReq: 68
Implicits: 1
{crafted}Used when Charges reach full
Gain 3 Charges when you are Hit by an Enemy
14% increased Movement Speed during Effect
			<ModRange range="0.5" id="3"/>
			<ModRange range="0.5" id="4"/>
		</Item>
		<Item variant="4" id="13">
			Rarity: UNIQUE
Taste of Hate
Sapphire Flask
Variant: Pre 2.2.0
Variant: Pre 3.0.0
Variant: Pre 3.15.0
Variant: Current
Selected Variant: 4
Sapphire Flask
Quality: 20
LevelReq: 18
Implicits: 1
{crafted}Used when Charges reach full
{variant:1}30% of Physical Damage from Hits taken as Cold Damage during Effect
{variant:2,3}20% of Physical Damage from Hits taken as Cold Damage during Effect
{variant:4}{range:1}(10-15)% of Physical Damage from Hits taken as Cold Damage during Effect
{variant:1,2}{range:0.5}Gain (20-30)% of Physical Damage as Extra Cold Damage during effect
{variant:3}{range:0.5}Gain (15-20)% of Physical Damage as Extra Cold Damage during effect
{variant:4}{range:0.5}Gain (10-15)% of Physical Damage as Extra Cold Damage during effect
30% chance to Avoid being Chilled during Effect
30% chance to Avoid being Frozen during Effect
			<ModRange range="0.5" id="4"/>
			<ModRange range="0.5" id="5"/>
			<ModRange range="1" id="6"/>
			<ModRange range="0.5" id="7"/>
			<ModRange range="0.5" id="8"/>
			<ModRange range="0.5" id="9"/>
			<ModRange range="0.5" id="10"/>
			<ModRange range="0.5" id="11"/>
		</Item>
		<Item id="14">
			Rarity: MAGIC
Flagellant&apos;s Quartz Flask of the Owl
Crafted: true
Prefix: {range:1}FlaskFullRechargeOnHit5___
Suffix: {range:0.947}FlaskBuffCurseEffect5
Quality: 20
LevelReq: 67
Implicits: 0
Gain 3 Charges when you are Hit by an Enemy
65% reduced Effect of Curses on you during Effect
			<ModRange range="0.5" id="3"/>
			<ModRange range="0.5" id="4"/>
		</Item>
		<Item id="15">
			Rarity: MAGIC
Flagellant&apos;s Silver Flask
Crafted: true
Prefix: {range:1}FlaskFullRechargeOnHit5___
Suffix: None
Quality: 20
LevelReq: 64
Implicits: 0
Gain 3 Charges when you are Hit by an Enemy
{tags:flask,unveiled_mod}{crafted}50% Chance to Avoid being Stunned during Effect
			<ModRange range="0.5" id="2"/>
			<ModRange range="0.5" id="3"/>
		</Item>
		<Item id="16">
			Rarity: RARE
Basic Bow
Maraketh Bow
Crafted: true
Prefix: None
Prefix: None
Prefix: None
Suffix: {range:1}GlobalDamageOverTimeMultiplier1h5
Suffix: None
Suffix: None
Quality: 20
Sockets: G-G-G-G-G-G
LevelReq: 71
Implicits: 1
{tags:speed}10% increased Movement Speed
+26% to Damage over Time Multiplier
{tags:dot_multi,chaos_damage,unveiled_mod,damage,chaos}{crafted}{range:1}+(18-20)% to Chaos Damage over Time Multiplier
			<ModRange range="0.5" id="1"/>
			<ModRange range="0.5" id="2"/>
			<ModRange range="1" id="3"/>
		</Item>
		<Item id="17">
			Rarity: RARE
Slightly Less Basic Bow
Maraketh Bow
Crafted: true
Prefix: {range:0.5}LocalIncreaseSocketedGemLevel1
Prefix: None
Prefix: None
Suffix: {range:1}GlobalDamageOverTimeMultiplier1h5
Suffix: None
Suffix: None
Quality: 20
Sockets: G-G-G-G-G-G
LevelReq: 71
Implicits: 1
{tags:speed}10% increased Movement Speed
+1 to Level of Socketed Gems
+26% to Damage over Time Multiplier
{tags:dot_multi,chaos_damage,unveiled_mod,damage,chaos}{crafted}{range:1}+(18-20)% to Chaos Damage over Time Multiplier
{crafted}Can have up to 3 Crafted Modifiers
{tags:physical_damage,chaos_damage,unveiled_mod,damage,physical,chaos}{crafted}{range:1}Gain (14-16)% of Physical Damage as Extra Chaos Damage
			<ModRange range="0.5" id="1"/>
			<ModRange range="0.5" id="2"/>
			<ModRange range="0.5" id="3"/>
			<ModRange range="1" id="4"/>
			<ModRange range="1" id="6"/>
		</Item>
		<ItemSet useSecondWeaponSet="false" id="1">
			<Slot itemPbURL="" name="Gloves" itemId="1"/>
			<Slot itemPbURL="" name="Weapon 1" itemId="3"/>
			<Slot itemPbURL="" name="Boots Abyssal Socket 5" itemId="0"/>
			<Slot itemPbURL="" name="Belt Abyssal Socket 2" itemId="0"/>
			<Slot itemPbURL="" active="true" name="Flask 3" itemId="13"/>
			<Slot itemPbURL="" name="Weapon 1 Swap Abyssal Socket 4" itemId="0"/>
			<Slot itemPbURL="" name="Weapon 1 Abyssal Socket 5" itemId="0"/>
			<Slot itemPbURL="" name="Weapon 2 Abyssal Socket 5" itemId="0"/>
			<SocketIdURL nodeId="60735" name="Jewel 60735" itemPbURL=""/>
			<Slot itemPbURL="" name="Weapon 1 Swap Abyssal Socket 6" itemId="0"/>
			<Slot itemPbURL="" name="Weapon 1 Abyssal Socket 6" itemId="0"/>
			<Slot itemPbURL="" name="Weapon 2 Abyssal Socket 6" itemId="0"/>
			<SocketIdURL nodeId="33989" name="Jewel 33989" itemPbURL=""/>
			<Slot itemPbURL="" name="Weapon 2 Swap Abyssal Socket 1" itemId="0"/>
			<SocketIdURL nodeId="54127" name="Jewel 54127" itemPbURL=""/>
			<Slot itemPbURL="" name="Boots Abyssal Socket 3" itemId="0"/>
			<Slot itemPbURL="" name="Weapon 1 Abyssal Socket 2" itemId="0"/>
			<Slot itemPbURL="" name="Weapon 2 Swap Abyssal Socket 4" itemId="0"/>
			<Slot itemPbURL="" name="Helmet Abyssal Socket 1" itemId="0"/>
			<Slot itemPbURL="" name="Belt Abyssal Socket 6" itemId="0"/>
			<Slot itemPbURL="" name="Helmet Abyssal Socket 2" itemId="0"/>
			<Slot itemPbURL="" name="Helmet" itemId="6"/>
			<Slot itemPbURL="" name="Helmet Abyssal Socket 3" itemId="0"/>
			<Slot itemPbURL="" name="Weapon 2 Swap Abyssal Socket 5" itemId="0"/>
			<Slot itemPbURL="" name="Weapon 1 Abyssal Socket 1" itemId="0"/>
			<Slot itemPbURL="" name="Weapon 2 Abyssal Socket 1" itemId="0"/>
			<Slot itemPbURL="" name="Weapon 1 Abyssal Socket 4" itemId="0"/>
			<Slot itemPbURL="" name="Belt" itemId="10"/>
			<Slot itemPbURL="" name="Weapon 1 Swap Abyssal Socket 2" itemId="0"/>
			<Slot itemPbURL="" name="Boots Abyssal Socket 4" itemId="0"/>
			<Slot itemPbURL="" name="Weapon 2 Abyssal Socket 2" itemId="0"/>
			<Slot itemPbURL="" active="true" name="Flask 5" itemId="15"/>
			<Slot itemPbURL="" name="Weapon 1 Swap Abyssal Socket 3" itemId="0"/>
			<Slot itemPbURL="" name="Boots Abyssal Socket 2" itemId="0"/>
			<Slot itemPbURL="" name="Belt Abyssal Socket 3" itemId="0"/>
			<Slot itemPbURL="" name="Body Armour Abyssal Socket 1" itemId="0"/>
			<Slot itemPbURL="" name="Gloves Abyssal Socket 1" itemId="0"/>
			<Slot itemPbURL="" name="Helmet Abyssal Socket 5" itemId="0"/>
			<Slot itemPbURL="" name="Helmet Abyssal Socket 6" itemId="0"/>
			<Slot itemPbURL="" name="Weapon 1 Swap Abyssal Socket 1" itemId="0"/>
			<Slot itemPbURL="" name="Weapon 2 Swap Abyssal Socket 2" itemId="0"/>
			<Slot itemPbURL="" active="true" name="Flask 1" itemId="11"/>
			<Slot itemPbURL="" name="Helmet Abyssal Socket 4" itemId="0"/>
			<Slot itemPbURL="" name="Gloves Abyssal Socket 5" itemId="0"/>
			<Slot itemPbURL="" name="Body Armour Abyssal Socket 2" itemId="0"/>
			<Slot itemPbURL="" name="Amulet" itemId="8"/>
			<Slot itemPbURL="" name="Weapon 1 Abyssal Socket 3" itemId="0"/>
			<Slot itemPbURL="" name="Weapon 2 Abyssal Socket 3" itemId="0"/>
			<Slot itemPbURL="" name="Belt Abyssal Socket 4" itemId="0"/>
			<Slot itemPbURL="" name="Belt Abyssal Socket 1" itemId="0"/>
			<Slot itemPbURL="" name="Body Armour Abyssal Socket 3" itemId="0"/>
			<Slot itemPbURL="" name="Weapon 2 Swap" itemId="0"/>
			<Slot itemPbURL="" active="true" name="Flask 4" itemId="14"/>
			<Slot itemPbURL="" active="true" name="Flask 2" itemId="12"/>
			<Slot itemPbURL="" name="Weapon 2" itemId="4"/>
			<Slot itemPbURL="" name="Belt Abyssal Socket 5" itemId="0"/>
			<Slot itemPbURL="" name="Boots Abyssal Socket 1" itemId="0"/>
			<Slot itemPbURL="" name="Body Armour Abyssal Socket 4" itemId="0"/>
			<Slot itemPbURL="" name="Weapon 2 Swap Abyssal Socket 6" itemId="0"/>
			<Slot itemPbURL="" name="Weapon 2 Swap Abyssal Socket 3" itemId="0"/>
			<Slot itemPbURL="" name="Weapon 1 Swap" itemId="0"/>
			<Slot itemPbURL="" name="Ring 2" itemId="9"/>
			<Slot itemPbURL="" name="Gloves Abyssal Socket 2" itemId="0"/>
			<Slot itemPbURL="" name="Body Armour Abyssal Socket 6" itemId="0"/>
			<Slot itemPbURL="" name="Weapon 1 Swap Abyssal Socket 5" itemId="0"/>
			<Slot itemPbURL="" name="Weapon 2 Abyssal Socket 4" itemId="0"/>
			<Slot itemPbURL="" name="Body Armour" itemId="2"/>
			<Slot itemPbURL="" name="Ring 1" itemId="9"/>
			<Slot itemPbURL="" name="Gloves Abyssal Socket 3" itemId="0"/>
			<Slot itemPbURL="" name="Body Armour Abyssal Socket 5" itemId="0"/>
			<Slot itemPbURL="" name="Gloves Abyssal Socket 4" itemId="0"/>
			<Slot itemPbURL="" name="Gloves Abyssal Socket 6" itemId="0"/>
			<Slot itemPbURL="" name="Boots" itemId="7"/>
			<Slot itemPbURL="" name="Boots Abyssal Socket 6" itemId="0"/>
		</ItemSet>
	</Items>
	<Config>
		<Input name="enemyIsBoss" string="Pinnacle"/>
		<Input name="usePowerCharges" boolean="true"/>
		<Input name="conditionUsingFlask" boolean="true"/>
		<Input name="pantheonMinorGod" string="Ralakesh"/>
		<Input name="useFrenzyCharges" boolean="true"/>
		<Input name="multiplierWitheredStackCount" number="15"/>
		<Input name="pantheonMajorGod" string="Solaris"/>
		<Placeholder name="enemySpeed" number="700"/>
		<Placeholder name="enemyChaosResist" number="30"/>
		<Placeholder name="enemyLightningDamage" number="2241"/>
		<Placeholder name="enemyCritChance" number="5"/>
		<Placeholder name="enemyFireResist" number="50"/>
		<Placeholder name="enemyColdDamage" number="2241"/>
		<Placeholder name="enemyFireDamage" number="2241"/>
		<Placeholder name="enemyLevel" number="84"/>
		<Placeholder name="enemyColdResist" number="50"/>
		<Placeholder name="enemyLightningPen" number="3"/>
		<Placeholder name="enemyLightningResist" number="50"/>
		<Placeholder name="enemyChaosDamage" number="896"/>
		<Placeholder name="enemyColdPen" number="3"/>
		<Placeholder name="enemyDamageRollRange" number="70"/>
		<Placeholder name="enemyArmour" number="24752"/>
		<Placeholder name="enemyFirePen" number="3"/>
		<Placeholder name="enemyPhysicalDamage" number="2241"/>
		<Placeholder name="enemyEvasion" number="10143"/>
		<Placeholder name="enemyCritDamage" number="30"/>
	</Config>
</PathOfBuilding>
